{"nodes": [{"id": "c_users_suvesh_desktop_qrcode_leaf_frontend_src_app_tsx", "label": "App.tsx", "file_type": "code", "source_file": "C:\\Users\\Suvesh\\Desktop\\qrcode leaf\\frontend\\src\\App.tsx", "source_location": "L1"}, {"id": "src_app_landingview", "label": "LandingView", "file_type": "code", "source_file": "C:\\Users\\Suvesh\\Desktop\\qrcode leaf\\frontend\\src\\App.tsx", "source_location": "L8"}, {"id": "src_app_generatorview", "label": "GeneratorView", "file_type": "code", "source_file": "C:\\Users\\Suvesh\\Desktop\\qrcode leaf\\frontend\\src\\App.tsx", "source_location": "L9"}, {"id": "src_app_dashboardview", "label": "DashboardView", "file_type": "code", "source_file": "C:\\Users\\Suvesh\\Desktop\\qrcode leaf\\frontend\\src\\App.tsx", "source_location": "L10"}, {"id": "src_app_templatesview", "label": "TemplatesView", "file_type": "code", "source_file": "C:\\Users\\Suvesh\\Desktop\\qrcode leaf\\frontend\\src\\App.tsx", "source_location": "L11"}, {"id": "src_app_docsview", "label": "DocsView", "file_type": "code", "source_file": "C:\\Users\\Suvesh\\Desktop\\qrcode leaf\\frontend\\src\\App.tsx", "source_location": "L12"}, {"id": "src_app_pricingview", "label": "PricingView", "file_type": "code", "source_file": "C:\\Users\\Suvesh\\Desktop\\qrcode leaf\\frontend\\src\\App.tsx", "source_location": "L13"}, {"id": "src_app_loginview", "label": "LoginView", "file_type": "code", "source_file": "C:\\Users\\Suvesh\\Desktop\\qrcode leaf\\frontend\\src\\App.tsx", "source_location": "L14"}, {"id": "src_app_signupview", "label": "SignupView", "file_type": "code", "source_file": "C:\\Users\\Suvesh\\Desktop\\qrcode leaf\\frontend\\src\\App.tsx", "source_location": "L15"}, {"id": "src_app_emptyview", "label": "EmptyView()", "file_type": "code", "source_file": "C:\\Users\\Suvesh\\Desktop\\qrcode leaf\\frontend\\src\\App.tsx", "source_location": "L18"}, {"id": "src_app_adminroute", "label": "AdminRoute()", "file_type": "code", "source_file": "C:\\Users\\Suvesh\\Desktop\\qrcode leaf\\frontend\\src\\App.tsx", "source_location": "L28"}, {"id": "src_app_app", "label": "App()", "file_type": "code", "source_file": "C:\\Users\\Suvesh\\Desktop\\qrcode leaf\\frontend\\src\\App.tsx", "source_location": "L42"}], "edges": [{"source": "c_users_suvesh_desktop_qrcode_leaf_frontend_src_app_tsx", "target": "react", "relation": "imports_from", "context": "import", "confidence": "EXTRACTED", "source_file": "C:\\Users\\Suvesh\\Desktop\\qrcode leaf\\frontend\\src\\App.tsx", "source_location": "L1", "weight": 1.0}, {"source": "c_users_suvesh_desktop_qrcode_leaf_frontend_src_app_tsx", "target": "react_router_dom", "relation": "imports_from", "context": "import", "confidence": "EXTRACTED", "source_file": "C:\\Users\\Suvesh\\Desktop\\qrcode leaf\\frontend\\src\\App.tsx", "source_location": "L2", "weight": 1.0}, {"source": "c_users_suvesh_desktop_qrcode_leaf_frontend_src_app_tsx", "target": "c_users_suvesh_desktop_qrcode_leaf_frontend_src_components_layout_applayout_tsx", "relation": "imports_from", "context": "import", "confidence": "EXTRACTED", "source_file": "C:\\Users\\Suvesh\\Desktop\\qrcode leaf\\frontend\\src\\App.tsx", "source_location": "L3", "weight": 1.0}, {"source": "c_users_suvesh_desktop_qrcode_leaf_frontend_src_app_tsx", "target": "c_users_suvesh_desktop_qrcode_leaf_frontend_src_components_layout_publiclayout_tsx", "relation": "imports_from", "context": "import", "confidence": "EXTRACTED", "source_file": "C:\\Users\\Suvesh\\Desktop\\qrcode leaf\\frontend\\src\\App.tsx", "source_location": "L4", "weight": 1.0}, {"source": "c_users_suvesh_desktop_qrcode_leaf_frontend_src_app_tsx", "target": "c_users_suvesh_desktop_qrcode_leaf_frontend_src_templatecontext_tsx", "relation": "imports_from", "context": "import", "confidence": "EXTRACTED", "source_file": "C:\\Users\\Suvesh\\Desktop\\qrcode leaf\\frontend\\src\\App.tsx", "source_location": "L5", "weight": 1.0}, {"source": "c_users_suvesh_desktop_qrcode_leaf_frontend_src_app_tsx", "target": "src_templatecontext_templateprovider", "relation": "imports", "context": "import", "confidence": "EXTRACTED", "source_file": "C:\\Users\\Suvesh\\Desktop\\qrcode leaf\\frontend\\src\\App.tsx", "source_location": "L5", "weight": 1.0}, {"source": "c_users_suvesh_desktop_qrcode_leaf_frontend_src_app_tsx", "target": "src_app_landingview", "relation": "contains", "confidence": "EXTRACTED", "source_file": "C:\\Users\\Suvesh\\Desktop\\qrcode leaf\\frontend\\src\\App.tsx", "source_location": "L8", "weight": 1.0}, {"source": "c_users_suvesh_desktop_qrcode_leaf_frontend_src_app_tsx", "target": "src_app_generatorview", "relation": "contains", "confidence": "EXTRACTED", "source_file": "C:\\Users\\Suvesh\\Desktop\\qrcode leaf\\frontend\\src\\App.tsx", "source_location": "L9", "weight": 1.0}, {"source": "c_users_suvesh_desktop_qrcode_leaf_frontend_src_app_tsx", "target": "src_app_dashboardview", "relation": "contains", "confidence": "EXTRACTED", "source_file": "C:\\Users\\Suvesh\\Desktop\\qrcode leaf\\frontend\\src\\App.tsx", "source_location": "L10", "weight": 1.0}, {"source": "c_users_suvesh_desktop_qrcode_leaf_frontend_src_app_tsx", "target": "src_app_templatesview", "relation": "contains", "confidence": "EXTRACTED", "source_file": "C:\\Users\\Suvesh\\Desktop\\qrcode leaf\\frontend\\src\\App.tsx", "source_location": "L11", "weight": 1.0}, {"source": "c_users_suvesh_desktop_qrcode_leaf_frontend_src_app_tsx", "target": "src_app_docsview", "relation": "contains", "confidence": "EXTRACTED", "source_file": "C:\\Users\\Suvesh\\Desktop\\qrcode leaf\\frontend\\src\\App.tsx", "source_location": "L12", "weight": 1.0}, {"source": "c_users_suvesh_desktop_qrcode_leaf_frontend_src_app_tsx", "target": "src_app_pricingview", "relation": "contains", "confidence": "EXTRACTED", "source_file": "C:\\Users\\Suvesh\\Desktop\\qrcode leaf\\frontend\\src\\App.tsx", "source_location": "L13", "weight": 1.0}, {"source": "c_users_suvesh_desktop_qrcode_leaf_frontend_src_app_tsx", "target": "src_app_loginview", "relation": "contains", "confidence": "EXTRACTED", "source_file": "C:\\Users\\Suvesh\\Desktop\\qrcode leaf\\frontend\\src\\App.tsx", "source_location": "L14", "weight": 1.0}, {"source": "c_users_suvesh_desktop_qrcode_leaf_frontend_src_app_tsx", "target": "src_app_signupview", "relation": "contains", "confidence": "EXTRACTED", "source_file": "C:\\Users\\Suvesh\\Desktop\\qrcode leaf\\frontend\\src\\App.tsx", "source_location": "L15", "weight": 1.0}, {"source": "c_users_suvesh_desktop_qrcode_leaf_frontend_src_app_tsx", "target": "src_app_emptyview", "relation": "contains", "confidence": "EXTRACTED", "source_file": "C:\\Users\\Suvesh\\Desktop\\qrcode leaf\\frontend\\src\\App.tsx", "source_location": "L18", "weight": 1.0}, {"source": "c_users_suvesh_desktop_qrcode_leaf_frontend_src_app_tsx", "target": "src_app_adminroute", "relation": "contains", "confidence": "EXTRACTED", "source_file": "C:\\Users\\Suvesh\\Desktop\\qrcode leaf\\frontend\\src\\App.tsx", "source_location": "L28", "weight": 1.0}, {"source": "c_users_suvesh_desktop_qrcode_leaf_frontend_src_app_tsx", "target": "src_app_app", "relation": "contains", "confidence": "EXTRACTED", "source_file": "C:\\Users\\Suvesh\\Desktop\\qrcode leaf\\frontend\\src\\App.tsx", "source_location": "L42", "weight": 1.0}], "raw_calls": [{"caller_nid": "src_app_adminroute", "callee": "getItem", "is_member_call": true, "source_file": "C:\\Users\\Suvesh\\Desktop\\qrcode leaf\\frontend\\src\\App.tsx", "source_location": "L29"}, {"caller_nid": "src_app_adminroute", "callee": "parse", "is_member_call": true, "source_file": "C:\\Users\\Suvesh\\Desktop\\qrcode leaf\\frontend\\src\\App.tsx", "source_location": "L33"}]}